{
  "classification": "Cuba",
  "document_type": "Memorandum of Contact",
  "security_level": "SECRET",
  "summary": "This memorandum details a contact with Jose Antonio CASAS Rodriguez regarding his knowledge of the Cuban situation and personalities, potential recruitment of Cuban officials, and operational proposals.",
  "tags": [
    "Jose Antonio CASAS Rodriguez",
    "Cuban situation",
    "personalities",
    "debriefing",
    "recruitment",
    "operational approach",
    "Esubio AZCUE",
    "Enrique RODRIGUEZ Loeches",
    "Orlando BLANCO",
    "Faure CHOMON Mediavilla",
    "Floreal CHOMON Mediavilla"
  ],
  "title": "MEMORANDUM OF CONTACT: Jose Antonio CASAS Rodriguez",
  "date": "1963-05-16",
  "locations_mentioned": [
    "Harrisburg, Pennsylvania",
    "216 Cumberland Street",
    "Miami",
    "Mexico City",
    "University of Habana",
    "Morocco",
    "Sierra Maestre",
    "Madrid",
    "USSR",
    "Moscow",
    "Camaguey",
    "Iraq",
    "Cuban Legation in Iraq",
    "Santiago de Cuba",
    "Habana",
    "Belgium",
    "Holguin, Cuba",
    "Willerate, Minnesota"
  ],
  "origin_agency": "CIA",
  "persons_mentioned": [
    "Jose Antonio CASAS Rodriguez",
    "Esubio AZCUE",
    "Fidel CASTRO",
    "Manolo CASTRO",
    "Enrique RODRIGUEZ Loeches",
    "BATISTA",
    "Orlando BLANCO",
    "Faure CHOMON Mediavilla",
    "Floreal CHOMON Mediavilla",
    "Carlos FIGARELLO",
    "JIMENEZ",
    "Santos JIMENEZ",
    "Jorge SERGUERA Pivieri",
    "Eduardo MACHADO Cartas",
    "Jose BARRIAL Dominguez",
    "Manuel PAYAN Viego",
    "Oscar PINO Santos",
    "Flora DIAZ Parrado",
    "Juan David POSADA",
    "Manuel R. MORALES",
    "Gustavo MEDIAVILLA de la Pena",
    "Lionel ALONSO Fiel",
    "Gustavo ROBRENO Dolz",
    "Jose R. LINARES Delgado",
    "Gustavo ARCOS y Bargnes",
    "Teresa PROENZA",
    "Silvino SORHEGUY Matos",
    "Jose Antonio PULIDO y Ledesma",
    "Armando PEREZ Pinto",
    "Juan JUARBE y Juarbo",
    "Laura MENESES de Albizu Campos",
    "Gilberto MEDIAVILLA",
    "Orlando PEREZ",
    "Eloy GUTIERREZ Menoyo",
    "GONZALEZ",
    "SAGARO",
    "Otto SKORZENY",
    "Raul RODRIGUEZ Feo",
    "Carlos LAC"
  ],
  "recipient": "C/SAS/CI",
  "sender": "Galen Peary, SAS/CI"
}