{
  "classification": "Cuba",
  "document_type": "Memorandum",
  "security_level": "SECRET",
  "summary": "This memorandum details a meeting with AMRUNG-1 regarding operations in Cuba, including discussions on security, operational expenditures, W/T operators, support for anti-Castro groups, and key individuals involved in the counter-revolutionary movement. It also covers attempts to supply the ANTUM group with arms and ammo, and air-maritime operations currently being planned.",
  "tags": [
    "AMRUNG-1",
    "Francisco",
    "Cuba",
    "Operations",
    "Counter-Revolutionary",
    "Arms Supply",
    "Security",
    "W/T Operators",
    "Manolo Ray",
    "Tony Varona",
    "FRD",
    "AMYUM"
  ],
  "title": "Contact Report on Meeting with AMRUNG-1",
  "date": "1960-11-08",
  "locations_mentioned": [
    "Cuba",
    "Havana",
    "Pinar del Rio",
    "Oriente",
    "Las Villas",
    "Camaguey"
  ],
  "origin_agency": "CIA",
  "persons_mentioned": [
    "AMRUNG-1",
    "DECKER",
    "Francisco",
    "Ray Carcia",
    "Andy Rogers",
    "Fodrick",
    "Cecil Cartwright",
    "Peters",
    "Rogers",
    "Castro",
    "PANIC-1",
    "ANGLEX-1",
    "APAC-1",
    "ANGLEN-1",
    "Manolo Ray",
    "Tony Varona",
    "Nino Dias",
    "AFRIDDY-1",
    "VARONA",
    "John D. Peters"
  ],
  "recipient": "Record",
  "sender": "John D. Peters"
}