{
  "classification": "Administrative",
  "document_type": "Memorandum",
  "security_level": "SECRET",
  "summary": "This memorandum discusses a meeting held to discuss the ramifications of a confrontation with the New York FBI office regarding Herbert Itkin. It also discusses Thomas L. Roberts' affiliation with the FBI, CIA, and Itkin, as well as Robert Delson's potential use in Projects DTPILLAR and WUBRINY.",
  "tags": [
    "Herbert Itkin",
    "Thomas L. Roberts",
    "Robert Delson",
    "FBI",
    "CIA",
    "Security Files",
    "DTPILLAR",
    "WUBRINY",
    "New York FBI"
  ],
  "title": "MEMORANDUM FOR THE RECORD SUBJECT: Herbert Itkin",
  "date": "1969-01-31",
  "locations_mentioned": [
    "New York",
    "Geneva",
    "Switzerland",
    "West Africa",
    "Dakar"
  ],
  "origin_agency": "CIA",
  "persons_mentioned": [
    "Herbert Itkin",
    "Rocca",
    "Houston",
    "Warner",
    "Thomas L. Roberts",
    "Robert Delson",
    "Ward Greene",
    "Eugene Milligan",
    "Robert Roberts",
    "Sam Papich",
    "John K. Greaney"
  ],
  "recipient": "FOR THE RECORD",
  "sender": "JOHN K. GREANEY, Assistant General Counsel"
}